esi_leap/__init__.py
esi_leap/send_email_notification.py
esi_leap/version.py
esi_leap/api/__init__.py
esi_leap/api/app.py
esi_leap/api/service.py
esi_leap/api/wsgi.py
esi_leap/api/controllers/__init__.py
esi_leap/api/controllers/base.py
esi_leap/api/controllers/root.py
esi_leap/api/controllers/types.py
esi_leap/api/controllers/version.py
esi_leap/api/controllers/v1/__init__.py
esi_leap/api/controllers/v1/console_auth_token.py
esi_leap/api/controllers/v1/event.py
esi_leap/api/controllers/v1/lease.py
esi_leap/api/controllers/v1/node.py
esi_leap/api/controllers/v1/offer.py
esi_leap/api/controllers/v1/root.py
esi_leap/api/controllers/v1/utils.py
esi_leap/api/controllers/v1/versions.py
esi_leap/cmd/__init__.py
esi_leap/cmd/api.py
esi_leap/cmd/dbsync.py
esi_leap/cmd/manager.py
esi_leap/cmd/serialconsoleproxy.py
esi_leap/common/__init__.py
esi_leap/common/constants.py
esi_leap/common/exception.py
esi_leap/common/health.py
esi_leap/common/i18n.py
esi_leap/common/ironic.py
esi_leap/common/keystone.py
esi_leap/common/notification_utils.py
esi_leap/common/policy.py
esi_leap/common/rpc.py
esi_leap/common/service.py
esi_leap/common/statuses.py
esi_leap/common/utils.py
esi_leap/conf/__init__.py
esi_leap/conf/api.py
esi_leap/conf/dummy_node.py
esi_leap/conf/ironic.py
esi_leap/conf/keystone.py
esi_leap/conf/netconf.py
esi_leap/conf/notification.py
esi_leap/conf/opts.py
esi_leap/conf/pecan.py
esi_leap/conf/serialconsoleproxy.py
esi_leap/console/__init__.py
esi_leap/console/websocketproxy.py
esi_leap/db/__init__.py
esi_leap/db/api.py
esi_leap/db/base.py
esi_leap/db/migration.py
esi_leap/db/sqlalchemy/__init__.py
esi_leap/db/sqlalchemy/alembic.ini
esi_leap/db/sqlalchemy/api.py
esi_leap/db/sqlalchemy/migration.py
esi_leap/db/sqlalchemy/models.py
esi_leap/db/sqlalchemy/alembic/README.md
esi_leap/db/sqlalchemy/alembic/__init__.py
esi_leap/db/sqlalchemy/alembic/env.py
esi_leap/db/sqlalchemy/alembic/script.py.mako
esi_leap-1.0.0.dist-info/AUTHORS
esi_leap-1.0.0.dist-info/LICENSE
esi_leap-1.0.0.dist-info/METADATA
esi_leap-1.0.0.dist-info/WHEEL
esi_leap-1.0.0.dist-info/entry_points.txt
esi_leap-1.0.0.dist-info/pbr.json
esi_leap-1.0.0.dist-info/top_level.txt
esi_leap-1.0.0.dist-info/RECORD
