Metadata-Version: 2.1
Name: esi-leap
Version: 1.0.0
Summary: ESI provider
Author: ESI
Author-email: esi@lists.massopen.cloud
License: Apache License, Version 2.0
Classifier: Environment :: Console
Classifier: Environment :: OpenStack
Classifier: Intended Audience :: Developers
Classifier: Intended Audience :: Information Technology
Classifier: Intended Audience :: System Administrators
Classifier: License :: OSI Approved :: Apache Software License
Classifier: Operating System :: OS Independent
Classifier: Programming Language :: Python
Classifier: Programming Language :: Python :: Implementation :: CPython
Classifier: Programming Language :: Python :: 3 :: Only
Classifier: Programming Language :: Python :: 3
Classifier: Programming Language :: Python :: 3.6
Classifier: Programming Language :: Python :: 3.7
Classifier: Programming Language :: Python :: 3.8
Requires-Python: >=3.6
License-File: LICENSE
License-File: AUTHORS
Requires-Dist: pbr !=2.1.0,>=2.0.0
Requires-Dist: alembic >=1.4.2
Requires-Dist: Babel !=2.4.0,>=2.3.4
Requires-Dist: eventlet >=0.33.3
Requires-Dist: iso8601 >=0.1.11
Requires-Dist: keystoneauth1 >=3.4.0
Requires-Dist: keystonemiddleware >=4.17.0
Requires-Dist: kombu !=4.0.2,>=4.0.0
Requires-Dist: mysql-connector-python >=8.0.0
Requires-Dist: openstacksdk <1.3.0
Requires-Dist: oslo.concurrency >=3.26.0
Requires-Dist: oslo.config >=5.2.0
Requires-Dist: oslo.db >=4.27.0
Requires-Dist: oslo.i18n >=3.15.3
Requires-Dist: oslo.log >=3.36.0
Requires-Dist: oslo.messaging >=5.29.0
Requires-Dist: oslo.middleware >=3.31.0
Requires-Dist: oslo.policy >=1.30.0
Requires-Dist: oslo.serialization !=2.19.1,>=2.18.0
Requires-Dist: oslo.service !=1.28.1,>=1.24.0
Requires-Dist: oslo.upgradecheck >=0.1.0
Requires-Dist: oslo.utils >=3.33.0
Requires-Dist: oslo.versionedobjects >=1.31.2
Requires-Dist: osprofiler >=1.5.0
Requires-Dist: netaddr >=0.7.18
Requires-Dist: python-ironicclient >=2.3.0
Requires-Dist: python-keystoneclient >=3.8.0
Requires-Dist: pecan !=1.0.2,!=1.0.3,!=1.0.4,!=1.2,>=1.0.0
Requires-Dist: PyMySQL >=0.7.6
Requires-Dist: sqlalchemy-migrate >=0.11.0
Requires-Dist: requests >=2.18.4
Requires-Dist: Routes >=2.3.1
Requires-Dist: six >=1.10.0
Requires-Dist: SQLAlchemy !=1.1.5,!=1.1.6,!=1.1.7,!=1.1.8,<2.0,>=1.0.10
Requires-Dist: stevedore >=1.20.0
Requires-Dist: WebOb >=1.7.1
Requires-Dist: websockify >=0.9.0
Requires-Dist: WSME >=0.8.0
Requires-Dist: importlib-metadata <5.0.0 ; (python_version<'3.8')
